{"is_source_file": false, "format": null, "description": null, "external_files": [], "external_methods": [], "published": [], "classes": [], "methods": [], "calls": [], "search-terms": [], "state": 2, "file_id": 3, "knowledge_revision": 22, "git_revision": "618195322842240fa006d36562cd1011da781d7d", "hash": "ad7806fb651cfca6b4ad75eea5d1f4a6", "format-version": 4, "code-base-name": "gaming_frontend", "filename": "gaming_frontend/README.md", "revision_history": [{"22": "618195322842240fa006d36562cd1011da781d7d"}]}